AUTHORS
CHANGELOG.md
MANIFEST.in
README.md
setup.cfg
setup.py
versioneer.py
src/libreflow/__init__.py
src/libreflow/thesiren_gui.py
src/libreflow.thesiren.egg-info/PKG-INFO
src/libreflow.thesiren.egg-info/SOURCES.txt
src/libreflow.thesiren.egg-info/dependency_links.txt
src/libreflow.thesiren.egg-info/requires.txt
src/libreflow.thesiren.egg-info/top_level.txt
src/libreflow/thesiren/__init__.py
src/libreflow/thesiren/_version.py
src/libreflow/thesiren/file.py
src/libreflow/thesiren/film.py
src/libreflow/thesiren/flow.py
src/libreflow/thesiren/lib.py
src/libreflow/thesiren/runners.py
src/libreflow/thesiren_custom_home/__init__.py
src/libreflow/thesiren_custom_home/ui.py
src/libreflow/thesiren_resources/__init__.py
src/libreflow/thesiren_resources/file_templates/__init__.py
src/libreflow/thesiren_resources/file_templates/template.blend
src/libreflow/thesiren_resources/gui/__init__.py
src/libreflow/thesiren_resources/gui/styles/__init__.py
src/libreflow/thesiren_resources/gui/styles/siren_style/__init__.py
src/libreflow/thesiren_resources/gui/styles/siren_style/siren_style.css