Metadata-Version: 2.1
Name: libreflow.thesiren
Version: 0.4.14
Summary: A Kabaret flow tailor-made for the production of a feature film
Home-page: https://gitlab.com/lfs.coop/libreflow
Author: Flavio Perez
Author-email: flavio@lfs.coop
License: LGPLv3+
Keywords: kabaret cgwire kitsu gazu animation pipeline libreflow
Platform: UNKNOWN
Classifier: Programming Language :: Python :: 3
Classifier: Intended Audience :: Developers
Classifier: Intended Audience :: End Users/Desktop
Classifier: Intended Audience :: Information Technology
Classifier: License :: OSI Approved :: GNU Lesser General Public License v3 or later (LGPLv3+)
Classifier: Operating System :: OS Independent
Requires-Python: >=3.7
License-File: AUTHORS
